skyz/__init__.py
skyz/compat.py
skyz/helpers.py
Skyz-0.1.dist-info/LICENSE.rst
Skyz-0.1.dist-info/METADATA
Skyz-0.1.dist-info/WHEEL
Skyz-0.1.dist-info/top_level.txt
Skyz-0.1.dist-info/RECORD
